git_remote_oracle/__init__.py
git_remote_oracle/git_remote_oracle.py
git_remote_oracle-0.0.5.dist-info/LICENSE
git_remote_oracle-0.0.5.dist-info/METADATA
git_remote_oracle-0.0.5.dist-info/WHEEL
git_remote_oracle-0.0.5.dist-info/entry_points.txt
git_remote_oracle-0.0.5.dist-info/top_level.txt
git_remote_oracle-0.0.5.dist-info/RECORD
